{
  "groups": [
    {
      "name": "task",
      "type": "com.wingflare.engine.task.server.common.config.SystemProperties",
      "sourceType": "com.wingflare.engine.task.server.common.config.SystemProperties"
    }
  ],
  "properties": [
    {
      "name": "task.callback",
      "type": "com.wingflare.engine.task.server.common.config.SystemProperties$Callback",
      "defaultValue": "30",
      "description": "服务端的地址，若服务端集群部署则此处配置域名",
      "sourceType": "com.wingflare.engine.task.server.common.config.SystemProperties"
    },
    {
      "name": "task.mail",
      "type": "com.wingflare.engine.task.common.core.alarm.email.TaskMailProperties",
      "description": "邮箱配置",
      "sourceType": "com.wingflare.engine.task.server.common.config.SystemProperties"
    }
  ]
}
